rtvs_archiver/__init__.py
rtvs_archiver/cli.py
rtvs_archiver/config.py
rtvs_archiver-0.1.1.dist-info/entry_points.txt
rtvs_archiver-0.1.1.dist-info/WHEEL
rtvs_archiver-0.1.1.dist-info/METADATA
rtvs_archiver-0.1.1.dist-info/RECORD
